{
  "border-radius-05": {
    "value": "2px",
    "description": "",
    "figmaName": ""
  },
  "border-radius-1": {
    "value": "4px",
    "description": "",
    "figmaName": ""
  },
  "border-radius-2": {
    "value": "8px",
    "description": "",
    "figmaName": ""
  },
  "border-radius-3": {
    "value": "12px",
    "description": "",
    "figmaName": ""
  },
  "border-radius-4": {
    "value": "16px",
    "description": "",
    "figmaName": ""
  },
  "border-radius-5": {
    "value": "20px",
    "description": "",
    "figmaName": ""
  },
  "border-radius-6": {
    "value": "30px",
    "description": "",
    "figmaName": ""
  },
  "border-radius-base": {
    "value": "3px",
    "description": "",
    "figmaName": ""
  },
  "border-radius-large": {
    "value": "6px",
    "description": "",
    "figmaName": ""
  },
  "border-radius-half": {
    "value": "50%",
    "description": "",
    "figmaName": ""
  },
  "border-width-1": {
    "value": "1px",
    "description": "",
    "figmaName": ""
  },
  "border-width-2": {
    "value": "2px",
    "description": "",
    "figmaName": ""
  },
  "border-width-3": {
    "value": "3px",
    "description": "",
    "figmaName": ""
  },
  "border-base": {
    "value": "var(--p-border-width-1) solid var(--p-border-subdued)",
    "description": "",
    "figmaName": ""
  },
  "border-dark": {
    "value": "var(--p-border-width-1) solid var(--p-border)",
    "description": "",
    "figmaName": ""
  },
  "border-transparent": {
    "value": "var(--p-border-width-1) solid transparent",
    "description": "",
    "figmaName": ""
  },
  "border-divider": {
    "value": "var(--p-border-width-1) solid var(--p-divider)",
    "description": "",
    "figmaName": ""
  }
}
